shopDB/Database.py
shopDB/__init__.py
shopDB_HalfBottleOfMind-1.0.5.dist-info/LICENSE
shopDB_HalfBottleOfMind-1.0.5.dist-info/METADATA
shopDB_HalfBottleOfMind-1.0.5.dist-info/WHEEL
shopDB_HalfBottleOfMind-1.0.5.dist-info/top_level.txt
shopDB_HalfBottleOfMind-1.0.5.dist-info/RECORD
