Metadata-Version: 2.1
Name: shopDB-HalfBottleOfMind
Version: 1.0.5
Summary: Shop database
Home-page: https://github.com/halfbottleofmind/shopdb
Author: HalfBottleOfMind
Author-email: andromalak222@gmail.com
License: UNKNOWN
Platform: UNKNOWN
Classifier: Programming Language :: Python :: 3.8
Classifier: License :: OSI Approved :: MIT License
Classifier: Operating System :: OS Independent
Requires-Python: >=3.8
